st_img_card/__init__.py
st_img_card/example.py
st_img_card/frontend/build/asset-manifest.json
st_img_card/frontend/build/bootstrap.min.css
st_img_card/frontend/build/index.html
st_img_card/frontend/build/static/js/main.d9d134cf.js
st_img_card/frontend/build/static/js/main.d9d134cf.js.LICENSE.txt
st_img_card/frontend/build/static/js/main.d9d134cf.js.map
st_img_card-0.0.1.dist-info/LICENSE
st_img_card-0.0.1.dist-info/METADATA
st_img_card-0.0.1.dist-info/WHEEL
st_img_card-0.0.1.dist-info/top_level.txt
st_img_card-0.0.1.dist-info/RECORD
